{
  "version": "7",
  "dialect": "postgresql",
  "entries": [
    {
      "idx": 0,
      "version": "7",
      "when": 1751206124937,
      "tag": "0000_glamorous_tarot",
      "breakpoints": true
    },
    {
      "idx": 1,
      "version": "7",
      "when": 1751769612528,
      "tag": "0001_rainy_energizer",
      "breakpoints": true
    },
    {
      "idx": 2,
      "version": "7",
      "when": 1751805074542,
      "tag": "0002_moaning_wiccan",
      "breakpoints": true
    },
    {
      "idx": 3,
      "version": "7",
      "when": 1752289163669,
      "tag": "0003_magical_reaper",
      "breakpoints": true
    },
    {
      "idx": 4,
      "version": "7",
      "when": 1752328349699,
      "tag": "0004_black_phil_sheldon",
      "breakpoints": true
    }
  ]
}